CHANGES.rst
MANIFEST.in
README.rst
setup.cfg
setup.py
Products/__init__.py
Products.PloneGlossary.egg-info/PKG-INFO
Products.PloneGlossary.egg-info/SOURCES.txt
Products.PloneGlossary.egg-info/dependency_links.txt
Products.PloneGlossary.egg-info/namespace_packages.txt
Products.PloneGlossary.egg-info/not-zip-safe
Products.PloneGlossary.egg-info/requires.txt
Products.PloneGlossary.egg-info/top_level.txt
Products/PloneGlossary/ABOUT
Products/PloneGlossary/LICENSE
Products/PloneGlossary/PloneGlossaryCatalog.py
Products/PloneGlossary/PloneGlossaryTool.py
Products/PloneGlossary/TODO.txt
Products/PloneGlossary/__init__.py
Products/PloneGlossary/config.py
Products/PloneGlossary/configure.zcml
Products/PloneGlossary/customconfig.py
Products/PloneGlossary/interfaces.py
Products/PloneGlossary/patches.py
Products/PloneGlossary/permissions.py
Products/PloneGlossary/product.txt
Products/PloneGlossary/rebuild_i18n.sh
Products/PloneGlossary/setuphandlers.py
Products/PloneGlossary/tool.gif
Products/PloneGlossary/utils.py
Products/PloneGlossary/Extensions/install.py
Products/PloneGlossary/browser/__init__.py
Products/PloneGlossary/browser/configure.zcml
Products/PloneGlossary/browser/pages.py
Products/PloneGlossary/browser/ploneglossary_portlet.pt
Products/PloneGlossary/browser/portlet.py
Products/PloneGlossary/content/PloneGlossary.py
Products/PloneGlossary/content/PloneGlossaryDefinition.py
Products/PloneGlossary/content/__init__.py
Products/PloneGlossary/content/schemata.py
Products/PloneGlossary/doc/FAQ
Products/PloneGlossary/doc/SCREENSHOTS
Products/PloneGlossary/doc/complete_example.png
Products/PloneGlossary/doc/icon.png
Products/PloneGlossary/examples/__init__.py
Products/PloneGlossary/examples/exampleglossary.py
Products/PloneGlossary/exportimport/__init__.py
Products/PloneGlossary/exportimport/configure.zcml
Products/PloneGlossary/exportimport/tool.py
Products/PloneGlossary/i18n/glossary-cs.po
Products/PloneGlossary/i18n/glossary-da.po
Products/PloneGlossary/i18n/glossary-de.po
Products/PloneGlossary/i18n/glossary-es.po
Products/PloneGlossary/i18n/glossary-fr.po
Products/PloneGlossary/i18n/glossary-it.po
Products/PloneGlossary/i18n/glossary-nl.po
Products/PloneGlossary/i18n/glossary-pl.po
Products/PloneGlossary/i18n/glossary-plone-cs.po
Products/PloneGlossary/i18n/glossary-plone-da.po
