Metadata-Version: 1.1
Name: Products.PloneGlossary
Version: 1.7.3
Summary: Highlight Plone content terms, mouseover shows the term definition as tooltip.
Home-page: https://github.com/collective/Products.PloneGlossary
Author: Ingeniweb
Author-email: support@ingeniweb.com
License: GPL
Keywords: plone glossary
Platform: UNKNOWN
Classifier: Programming Language :: Python
Classifier: Programming Language :: Python :: 2.4
Classifier: Programming Language :: Python :: 2.6
Classifier: Programming Language :: Python :: 2.7
Classifier: Framework :: Plone
Classifier: Framework :: Plone :: 3.2
Classifier: Framework :: Plone :: 3.3
Classifier: Framework :: Plone :: 4.0
Classifier: Framework :: Plone :: 4.1
Classifier: Framework :: Plone :: 4.2
Classifier: Framework :: Plone :: 4.3
Classifier: Topic :: Software Development :: Libraries :: Python Modules
